geolayer/__init__.py
geolayer/settings.py
geolayer/api/__init__.py
geolayer/api/rasterAPI.py
geolayer/api/redisAPI.py
geolayer/api/vectorAPI.py
geolayer/api/vrtAPI.py
geolayer/layer/__init__.py
geolayer/layer/composite_layer.py
geolayer/layer/raster_layer.py
geolayer/layer/vector_layer.py
geolayer/layer/fonts/__init__.py
geolayer/templates/__init__.py
geolayer/utility/__init__.py
geolayer/utility/classifiers.py
geolayer/utility/exceptions.py
geolayer/utility/templates.py
geolayer-0.0.7.dist-info/.ipynb_checkpoints/PKG-INFO-checkpoint
geolayer-0.0.7.dist-info/.ipynb_checkpoints/SOURCES-checkpoint.txt
geolayer-0.0.7.dist-info/.ipynb_checkpoints/dependency_links-checkpoint.txt
geolayer-0.0.7.dist-info/.ipynb_checkpoints/requires-checkpoint.txt
geolayer-0.0.7.dist-info/.ipynb_checkpoints/top_level-checkpoint.txt
geolayer-0.0.7.dist-info/LICENCE
geolayer-0.0.7.dist-info/METADATA
geolayer-0.0.7.dist-info/WHEEL
geolayer-0.0.7.dist-info/top_level.txt
geolayer-0.0.7.dist-info/RECORD
