Metadata-Version: 2.1
Name: geolayer
Version: 0.0.7
Summary: Display raster and vector geospatial data from a tilegeo server
Home-page: https://geolayer.readthedocs.io/en/latest/
Author: Davide De Marchi
Author-email: Davide De Marchi <davide.de-marchi@ec.europa.eu>, Edoardo Ramalli <edoardo.ramalli@ec.europa.eu>
Maintainer-email: Davide De Marchi <davide.de-marchi@ec.europa.eu>, Edoardo Ramalli <edoardo.ramalli@ec.europa.eu>
License: Copyright © European Union 2023-2024
Project-URL: homepage, https://github.com/DavideDeMarchi/geolayer
Project-URL: Bug Reports, https://github.com/DavideDeMarchi/geolayer/issues
Project-URL: documentation, https://geolayer.readthedocs.io/en/latest/
Project-URL: Source, https://github.com/DavideDeMarchi/geolayer/
Project-URL: repository, https://github.com/DavideDeMarchi/geolayer/
Keywords: Geospatial,raster,vector,visualisation,mapnik,setuptools,development
Classifier: Development Status :: 4 - Beta
Classifier: Intended Audience :: Developers
Classifier: Topic :: Software Development :: Build Tools
Classifier: License :: OSI Approved :: European Union Public Licence 1.2 (EUPL 1.2)
Classifier: Programming Language :: Python :: 3
Classifier: Programming Language :: Python :: 3.9
Classifier: Programming Language :: Python :: 3.10
Classifier: Programming Language :: Python :: 3.11
Classifier: Programming Language :: Python :: 3.12
Classifier: Programming Language :: Python :: 3 :: Only
Requires-Python: >=3.9
License-File: LICENCE
Requires-Dist: Pillow>=9.4.0
Requires-Dist: traitlets>=5.9.0
Requires-Dist: ipywidgets>=7.7.0
Requires-Dist: requests>=2.28.0
Requires-Dist: ipykernel
Requires-Dist: pandas
Requires-Dist: ipyvuetify
Requires-Dist: plotly
Requires-Dist: ipyleaflet
Requires-Dist: scikit-learn
Requires-Dist: scipy
